metofficeamd/__init__.py
metofficeamd/app.py
metofficeamd/base.py
metofficeamd/constants.py
metofficeamd/models.py
metofficeamd-0.0.4.dist-info/LICENSE
metofficeamd-0.0.4.dist-info/METADATA
metofficeamd-0.0.4.dist-info/WHEEL
metofficeamd-0.0.4.dist-info/top_level.txt
metofficeamd-0.0.4.dist-info/RECORD
