Metadata-Version: 2.1
Name: metofficeamd
Version: 0.0.4
Summary: Python wrapper for Met Office Weather DataHub AMD API
Home-page: UNKNOWN
Author: Peter Dudfield
Author-email: info@openclimatefix.org
License: MIT
Platform: UNKNOWN
License-File: LICENSE
Requires-Dist: pydantic
Requires-Dist: requests
Requires-Dist: pre-commit
Requires-Dist: ecmwflibs
Requires-Dist: eccodes
Requires-Dist: cfgrib
Requires-Dist: xarray
